MANIFEST.in
README.md
setup.py
scrapy_newrabbit/VERSION
scrapy_newrabbit/__init__.py
scrapy_newrabbit/cmdline.py
scrapy_newrabbit.egg-info/PKG-INFO
scrapy_newrabbit.egg-info/SOURCES.txt
scrapy_newrabbit.egg-info/dependency_links.txt
scrapy_newrabbit.egg-info/entry_points.txt
scrapy_newrabbit.egg-info/not-zip-safe
scrapy_newrabbit.egg-info/top_level.txt
scrapy_newrabbit/commands/__init__.py
scrapy_newrabbit/commands/genspider.py
scrapy_newrabbit/commands/startproject.py
scrapy_newrabbit/conf/__init__.py
scrapy_newrabbit/conf/confer.py
scrapy_newrabbit/core/__init__.py
scrapy_newrabbit/core/engine.py
scrapy_newrabbit/core/run.py
scrapy_newrabbit/http/__init__.py
scrapy_newrabbit/http/req.py
scrapy_newrabbit/rabbitmq/__init__.py
scrapy_newrabbit/rabbitmq/rabbit.py
scrapy_newrabbit/settings/__init__.py
scrapy_newrabbit/settings/default_settings.py
scrapy_newrabbit/templates/__init__.py
scrapy_newrabbit/templates/project/__init__.py
scrapy_newrabbit/templates/project/rabbitmq_delect.py.tmpl
scrapy_newrabbit/templates/project/scrapy.cfg
scrapy_newrabbit/templates/project/module/__init__.py
scrapy_newrabbit/templates/project/module/items.py.tmpl
scrapy_newrabbit/templates/project/module/middlewares.py.tmpl
scrapy_newrabbit/templates/project/module/pipelines.py.tmpl
scrapy_newrabbit/templates/project/module/settings.py.tmpl
scrapy_newrabbit/templates/project/module/conf/__init__.py
scrapy_newrabbit/templates/project/module/conf/config.ini
scrapy_newrabbit/templates/project/module/libs/__init__.py
scrapy_newrabbit/templates/project/module/libs/lib.py
scrapy_newrabbit/templates/project/module/spiders/__init__.py
scrapy_newrabbit/templates/spiders/__init__.py
scrapy_newrabbit/templates/spiders/basic.tmpl
scrapy_newrabbit/utils/__init__.py
scrapy_newrabbit/utils/loadspider.py
scrapy_newrabbit/utils/misc.py
scrapy_newrabbit/utils/pipelines.py
scrapy_newrabbit/utils/project.py
scrapy_newrabbit/utils/template.py