Metadata-Version: 2.1
Name: scrapy-newrabbit
Version: 1.1.2
Summary: Scrapy_NewRabbit
Home-page: UNKNOWN
Author: LinShu
Author-email: 1419282435@qq.com
License: MIT
Platform: UNKNOWN
Classifier: Programming Language :: Python :: 3
Classifier: License :: OSI Approved :: MIT License
Classifier: Operating System :: OS Independent
Requires-Python: >=3.6
